<?xml version="1.0" encoding="euc-kr"?>
<!-- 모든 태그의 이름과 속성 이름은 영어 소문자(줄임말, 고유명사의 시작 알파벳 제외)와 언더바(_)로 작성하며, -->
<!-- 속성값과 텍스트의 경우 한글로 형식을 맞추어 적는다. -->
<!-- 속성 이름과 = 기호, "속성값" 사이에는 공백이 없어야 한다. -->
<!-- 모든 속성과 태그는 사전을 참고하여 범용적인 단어로 골라 쓴다. -->
<!-- 모든 역명에는 "역"을 붙인다. (예: 안심역) -->
<!-- 모든 지역명은 "XX시" 형태로 작성한다. 특별, 광역 등 "시" 앞의 글자는 뗀다. -->
<!-- 고유명사의 경우, 위키 등을 참고하여 공식적인 영문명으로 쓴다. -->
<!-- 모든 지하철 정차역은 역 id를 기준으로 오름차순으로 작성한다. -->
<!-- mark는 'XX(건물이름)역'에서 건물이름에 해당하는 요소로, 나무위키 기준으로 존재하는 역만 적는다.-->
<!-- next_distance는 다음역과의 거리(km)를 실수로 나타낸 것으로, 종점역과 개통예정역을 제외한 모든 역에 적는다. -->
<!-- 개통예정 정차역의 경우, type을 normal로 통일한다. 종점역은 개통된 역만을 기준으로 한다. -->
<!-- 모든 기차 정차역은 필수정차역, 선택정차역을 모두 아울러 중부-남부 지방 순으로 작성한다. -->
<!-- 내용 변경 및 오탈자 수정 시, 아래의 양식에 맞추어 로그(기록)를 남겨주기 바람. -->

<!-- 변경사항 (작성: YYYY.MM.DD, 홍길동) -->
<!-- 전체 구조 디자인 및 1호선 정보 작성 (작성: 2023.11.21, 최유정) -->

<!-- 해당 지역을 지나는 철도의 정보를 정리한다. -->
<railroad region="대구시">
	<!-- 지하철을 노선-정차역 별로 분류하여 정리한다. -->
	<subway co="대구교통공사">
		<line1 type="지하">
			<station id="115" type="first" pub="open">
				<name lang="ko">설화명곡역</name>
				<name lang="en">SeolhwaMyeonggok</name>
				<region>대구시</region>
				<gu>달성군</gu>
				<next_distance>1.2</next_distance>
			</station>
			<station id="116" type="normal" pub="open">
				<name lang="ko">화원역</name>
				<name lang="en">Hwawon</name>
				<region>대구시</region>
				<gu>달성군</gu>
				<next_distance>1.3</next_distance>
			</station>
			<station id="117" type="normal" pub="open">
				<name lang="ko">대곡역</name>
				<name lang="en">Daegok</name>
				<region>대구시</region>
				<gu>달서구</gu>
				<mark>정부대구청사</mark>
				<next_distance>1.1</next_distance>
			</station>
			<station id="118" type="normal" pub="open">
				<name lang="ko">진천역</name>
				<name lang="en">Jincheon</name>
				<region>대구시</region>
				<gu>달서구</gu>
				<mark>보강병원</mark>
				<next_distance>0.8</next_distance>
			</station>
			<station id="119" type="normal" pub="open">
				<name lang="ko">월배역</name>
				<name lang="en">Wolbae</name>
				<region>대구시</region>
				<gu>달서구</gu>
				<next_distance>0.7</next_distance>
			</station>
			<station id="120" type="normal" pub="open">
				<name lang="ko">상인역</name>
				<name lang="en">Sangin</name>
				<region>대구시</region>
				<gu>달서구</gu>
				<mark>대구보훈병원</mark>
				<next_distance>0.9</next_distance>
			</station>
			<station id="121" type="normal" pub="open">
				<name lang="ko">월촌역</name>
				<name lang="en">Wolchon</name>
				<region>대구시</region>
				<gu>달서구</gu>
				<next_distance>1.0</next_distance>
			</station>
			<station id="122" type="normal" pub="open">
				<name lang="ko">송현역</name>
				<name lang="en">Songhyeon</name>
				<region>대구시</region>
				<gu>달서구</gu>
				<mark>참조은병원</mark>
				<next_distance>0.8</next_distance>
			</station>
			<station id="123" type="normal" pub="open">
				<name lang="ko">서부정류장역</name>
				<name lang="en">Seobu Bus Terminal</name>
				<region>대구시</region>
				<gu>남구</gu>
				<mark>관문시장·대구공업대학교</mark>
				<next_distance>0.8</next_distance>
			</station>
			<station id="124" type="normal" pub="open">
				<name lang="ko">대명역</name>
				<name lang="en">Daemyeong</name>
				<region>대구시</region>
				<gu>남구</gu>
				<next_distance>0.8</next_distance>
			</station>
			<station id="125" type="normal" pub="open">
				<name lang="ko">안지랑역</name>
				<name lang="en">Anjirang</name>
				<region>대구시</region>
				<gu>남구</gu>
				<mark>대구가톨릭대학교병원</mark>
				<next_distance>0.7</next_distance>
			</station>
			<station id="126" type="normal" pub="open">
				<name lang="ko">현충로역</name>
				<name lang="en">Hyeonchungno</name>
				<region>대구시</region>
				<gu>남구</gu>
				<next_distance>0.7</next_distance>
			</station>
			<station id="127" type="normal" pub="open">
				<name lang="ko">영대병원역</name>
				<name lang="en">Yeungnam Univ. Hospital</name>
				<region>대구시</region>
				<gu>남구</gu>
				<mark>영남이공대학교</mark>
				<next_distance>0.9</next_distance>
			</station>
			<station id="128" type="normal" pub="open">
				<name lang="ko">교대역</name>
				<name lang="en">Nat'l Univ. of Education</name>
				<region>대구시</region>
				<gu>남구</gu>
				<next_distance>0.8</next_distance>
			</station>
			<station id="129" type="transfer" to='line1' pub="open">
				<name lang="ko">명덕역</name>
				<name lang="en">Myeongdeok</name>
				<region>대구시</region>
				<gu>중구</gu>
				<mark>2.28민주운동기념회관</mark>
				<next_distance>0.8</next_distance>
			</station>
			<station id="130" type="transfer" to='line2' pub="open">
				<name lang="ko">반월당역</name>
				<name lang="en">Banwoldang</name>
				<region>대구시</region>
				<gu>중구</gu>
				<mark>스타법무법인</mark>
				<next_distance>0.7</next_distance>
			</station>
			<station id="131" type="normal" pub="open">
				<name lang="ko">중앙로역</name>
				<name lang="en">Jungangno</name>
				<region>대구시</region>
				<gu>중구</gu>
				<next_distance>0.7</next_distance>
			</station>
			<station id="132" type="train" pub="open">
				<name lang="ko">대구역</name>
				<name lang="en">Daegu Station</name>
				<region>대구시</region>
				<gu>북구</gu>
				<next_distance>0.8</next_distance>
			</station>
			<station id="133" type="normal" pub="open">
				<name lang="ko">칠성시장역</name>
				<name lang="en">Chilseong Market</name>
				<region>대구시</region>
				<gu>북구</gu>
				<mark>MS재건병원</mark>
				<next_distance>1.3</next_distance>
			</station>
			<station id="134" type="normal" pub="open">
				<name lang="ko">신천역</name>
				<name lang="en">Sincheon</name>
				<region>대구시</region>
				<gu>동구</gu>
				<mark>경북대입구</mark>
				<next_distance>0.9</next_distance>
			</station>
			<station id="135" type="train" pub="open">
				<name lang="ko">동대구역</name>
				<name lang="en">Dongdaegu Station</name>
				<region>대구시</region>
				<gu>동구</gu>
				<next_distance>0.9</next_distance>
			</station>
			<station id="136" type="normal" pub="open">
				<name lang="ko">동구청역</name>
				<name lang="en">Dong-gu Office</name>
				<region>대구시</region>
				<gu>동구</gu>
				<mark>큰고개</mark>
				<next_distance>0.8</next_distance>
			</station>
			<station id="137" type="normal" pub="open">
				<name lang="ko">아양교역</name>
				<name lang="en">Ayanggyo</name>
				<region>대구시</region>
				<gu>동구</gu>
				<mark>대구국제공항입구</mark>
			</station>
			<station id="138" type="normal" pub="open">
				<name lang="ko">동촌역</name>
				<name lang="en">Dongchon</name>
				<region>대구시</region>
				<gu>동구</gu>
				<mark>동촌유원지</mark>
				<next_distance>1.1</next_distance>
			</station>
			<station id="139" type="normal" pub="open">
				<name lang="ko">해안역</name>
				<name lang="en">Haean</name>
				<region>대구시</region>
				<gu>동구</gu>
				<next_distance>1.0</next_distance>
			</station>
			<station id="140" type="normal" pub="open">
				<name lang="ko">방촌역</name>
				<name lang="en">Bangchon</name>
				<region>대구시</region>
				<gu>동구</gu>
				<next_distance>1.1</next_distance>
			</station>
			<station id="141" type="normal" pub="open">
				<name lang="ko">용계역</name>
				<name lang="en">Yonggye</name>
				<region>대구시</region>
				<gu>동구</gu>
				<next_distance>1.2</next_distance>
			</station>
			<station id="142" type="normal" pub="open">
				<name lang="ko">율하역</name>
				<name lang="en">Yulha</name>
				<region>대구시</region>
				<gu>동구</gu>
				<mark>항시원외과</mark>
				<next_distance>1.1</next_distance>
			</station>
			<station id="143" type="normal" pub="open">
				<name lang="ko">신기역</name>
				<name lang="en">Singi</name>
				<region>대구시</region>
				<gu>동구</gu>
				<mark>신기한속내과의원</mark>
				<next_distance>1.0</next_distance>
			</station>
			<station id="144" type="normal" pub="open">
				<name lang="ko">반야월역</name>
				<name lang="en">Banyawol</name>
				<region>대구시</region>
				<gu>동구</gu>
				<next_distance>1.0</next_distance>
			</station>
			<station id="145" type="normal" pub="open">
				<name lang="ko">각산역</name>
				<name lang="en">Gaksan</name>
				<region>대구시</region>
				<gu>동구</gu>
				<mark>속안심내과연합의원</mark>
				<next_distance>0.9</next_distance>
			</station>
			<station id="146" type="last" pub="open">
				<name lang="ko">안심역</name>
				<name lang="en">Ansim</name>
				<region>대구시</region>
				<gu>동구</gu>
				<mark>혁신도시·첨복단지</mark>
			</station>

			<station id="147" type="normal" pub="due">
				<name lang="ko">대구한의대병원역</name>
				<name lang="en">Daegu Haany University Hospital</name>
				<region>대구시</region>
				<gu>동구</gu>
			</station>
			<station id="148" type="normal" pub="due">
				<name lang="ko">부호경일대호산대역</name>
				<name lang="en">Buho, Kyungil University, and Hosan University</name>
				<region>경산시</region>
				<gu>하양읍</gu>
			</station>
			<station id="149" type="normal" pub="due">
				<name lang="ko">하양대구가톨릭대역</name>
				<name lang="en">Hayang Daegu Catholic University</name>
				<region>경산시</region>
				<gu>하양읍</gu>
			</station>
		</line1>

		<line2 type="지하">
			<station id="216" type="first" pub="open">
				<name lang="ko">문양역</name>
				<name lang="en">Munyang</name>
				<region>대구시</region>
				<gu>달성군</gu>
				<next_distance>2.9</next_distance>
			</station>
			<station id="217" type="normal" pub="open">
				<name lang="ko">다사역</name>
				<name lang="en">Dasa</name>
				<region>대구시</region>
				<gu>달성군</gu>
				<next_distance>1.0</next_distance>
			</station>
			<station id="218" type="normal" pub="open">
				<name lang="ko">대실역</name>
				<name lang="en">Daesil</name>
				<region>대구시</region>
				<gu>달성군</gu>
				<mark>죽곡연합통증의학과</mark>
				<next_distance>1.4</next_distance>
			</station>
		</line2>
		
		<line3 type="지상">
		</line3>
	</subway>
	
	<!-- 기차를 열차종류-정차역 별로 분류하여 정리한다. -->
	<train co="한국철도공사">
		<ITX_Saemaeul line="경부선" speed="일반">
		</ITX_Saemaeul>
		
		<Mugunghwa_Ho line="경부선" speed="일반">
			<station stop="necessary" type="last">
				<name lang="ko">서울역</name>
				<region>서울시</region>
			</station>
			<station stop="selective" type="normal">
				<name lang="ko">안양역</name>
				<region></region>
			</station>
			<station stop="necessary" type="normal">
				<name lang="ko">동대구역</name>
				<region>대구시</region>
			</station>
		</Mugunghwa_Ho>
		
		<KTX line="경부선" speed="고속">
		</KTX>
		
		<KTX line="경부선" speed="일반">
		</KTX>
	</train>
</railroad>
